imap/__init__.py
imap/imap.py
sftp/__init__.py
sftp/sftp.py
smtp/__init__.py
smtp/smtp.py
sftp_smtp_imap-1.0.4.dist-info/LICENSE.txt
sftp_smtp_imap-1.0.4.dist-info/METADATA
sftp_smtp_imap-1.0.4.dist-info/WHEEL
sftp_smtp_imap-1.0.4.dist-info/top_level.txt
sftp_smtp_imap-1.0.4.dist-info/RECORD
