Metadata-Version: 2.1
Name: sftp-smtp-imap
Version: 1.0.4
Summary: This package includes functionality to work with any SFTP, IMAP and SMTP server
Home-page: https://github.com/SUNESHPANDITA/sftp-smtp-imap-package.git
Author: Sunesh Pandita
Author-email: suneshpandita2009@gmail.com
License: Copyright 2024 @Sunesh Pandita
Platform: Windows
Requires-Python: >=3.9.0
License-File: LICENSE.txt
